example/__init__.py
example/main.py
watched_sdk/__init__.py
watched_sdk/addon.py
watched_sdk/auth.py
watched_sdk/cache.py
watched_sdk/common.py
watched_sdk/config.py
watched_sdk/context.py
watched_sdk/exceptions.py
watched_sdk/main.py
watched_sdk/router.py
watched_sdk/test.py
watched_sdk/views.py
watched_sdk-0.3.2.dist-info/METADATA
watched_sdk-0.3.2.dist-info/WHEEL
watched_sdk-0.3.2.dist-info/top_level.txt
watched_sdk-0.3.2.dist-info/RECORD
