Metadata-Version: 2.1
Name: watched-sdk
Version: 0.3.2
Summary: WATCHED.com Python SDK
Home-page: https://github.com/watchedcom/sdk-python
Author: WATCHED
Author-email: dev@watched.com
License: UNKNOWN
Platform: UNKNOWN
Requires-Python: >=3.4
Requires-Dist: watched-schema (>=0.6.0)
Requires-Dist: diskcache
Requires-Dist: redis
Requires-Dist: flask
Requires-Dist: requests
Requires-Dist: markdown
